HSV/hsv.cp38-win_amd64.pyd
HSV/testing.cp38-win_amd64.pyd
HSV-1.0.2.data/data/lib/site-packages/HSV/LICENSE
HSV-1.0.2.data/data/lib/site-packages/HSV/MANIFEST.in
HSV-1.0.2.data/data/lib/site-packages/HSV/__init__.pxd
HSV-1.0.2.data/data/lib/site-packages/HSV/__init__.py
HSV-1.0.2.data/data/lib/site-packages/HSV/example.py
HSV-1.0.2.data/data/lib/site-packages/HSV/hsv.pxd
HSV-1.0.2.data/data/lib/site-packages/HSV/hsv.pyx
HSV-1.0.2.data/data/lib/site-packages/HSV/hsv_c.c
HSV-1.0.2.data/data/lib/site-packages/HSV/pyproject.toml
HSV-1.0.2.data/data/lib/site-packages/HSV/requirements.txt
HSV-1.0.2.data/data/lib/site-packages/HSV/setup_hsv.py
HSV-1.0.2.data/data/lib/site-packages/HSV/testing.pyx
HSV-1.0.2.data/data/lib/site-packages/HSV/test/HSV_testing.py
HSV-1.0.2.dist-info/LICENSE
HSV-1.0.2.dist-info/METADATA
HSV-1.0.2.dist-info/WHEEL
HSV-1.0.2.dist-info/top_level.txt
HSV-1.0.2.dist-info/RECORD
